Metadata-Version: 2.1
Name: cushy-serial
Version: 1.1.0
Summary: A lightweight serial library
Home-page: https://github.com/Undertone0809/cushy-serial
Author: Zeeland
Author-email: zeeland@foxmail.com
License: Apache 2.0
Keywords: serial,cushy-serial
Classifier: Development Status :: 3 - Alpha
Classifier: Intended Audience :: Developers
Classifier: Programming Language :: Python :: 3
Classifier: Programming Language :: Python :: 3.7
Classifier: Programming Language :: Python :: 3.8
Classifier: Programming Language :: Python :: 3.9
Classifier: Programming Language :: Python :: 3.10
Classifier: Programming Language :: Python :: 3 :: Only
Classifier: License :: OSI Approved :: MIT License
Classifier: Operating System :: OS Independent
License-File: LICENSE
